CHANGELOG.txt
LICENCE.txt
MANIFEST.in
README.txt
setup.py
dividecalc/__init__.py
dividecalc/spdivideCalc.py
spdividecalc.egg-info/PKG-INFO
spdividecalc.egg-info/SOURCES.txt
spdividecalc.egg-info/dependency_links.txt
spdividecalc.egg-info/top_level.txt